Metadata-Version: 2.1
Name: funnymessages
Version: 0.0.1
Summary: Display funny messages to the users
Home-page: 
Author: Andre Fagundes
Author-email: afagund@gmail.com
License: MIT
Keywords: funnymessages
Classifier: Development Status :: 5 - Production/Stable
Classifier: Intended Audience :: Developers
Classifier: Operating System :: POSIX :: Linux
Classifier: License :: OSI Approved :: MIT License
Classifier: Programming Language :: Python :: 3
License-File: LICENSE.txt
